pyspectroworks/__init__.py
pyspectroworks/pyspectroworks.py
pyspectroworks-1.0.1.dist-info/METADATA
pyspectroworks-1.0.1.dist-info/WHEEL
pyspectroworks-1.0.1.dist-info/licenses/LICENSE
pyspectroworks-1.0.1.dist-info/RECORD
