Metadata-Version: 2.1
Name: pyspectroworks
Version: 1.0.1
Summary: pySpectroWorks is a Python module for loading data from SpectroWorks™.
Project-URL: Homepage, https://github.com/cphnano/pySpectroWorks
Project-URL: Bug Tracker, https://github.com/cphnano/pySpectroWorks/issues
Author-email: Thomas Sørensen <thots@cphnano.com>
License-File: LICENSE
Classifier: Development Status :: 5 - Production/Stable
Classifier: License :: OSI Approved :: MIT License
Classifier: Operating System :: OS Independent
Classifier: Programming Language :: Python :: 3
Requires-Python: >=3.7
